{
  "hash": "ae86d81b",
  "configHash": "35ff2117",
  "lockfileHash": "29b4766e",
  "browserHash": "d2629334",
  "optimized": {
    "react": {
      "src": "../../node_modules/react/index.js",
      "file": "react.js",
      "fileHash": "827a5893",
      "needsInterop": true
    },
    "react-dom/client": {
      "src": "../../node_modules/react-dom/client.js",
      "file": "react-dom_client.js",
      "fileHash": "a0837113",
      "needsInterop": true
    },
    "react-router-dom": {
      "src": "../../node_modules/react-router-dom/dist/index.mjs",
      "file": "react-router-dom.js",
      "fileHash": "aca0617d",
      "needsInterop": false
    }
  },
  "chunks": {
    "chunk-4J6BLW67": {
      "file": "chunk-4J6BLW67.js"
    },
    "chunk-WYQRYOQT": {
      "file": "chunk-WYQRYOQT.js"
    }
  }
}